mpl_svg/__init__.py
mpl_svg/demo.py
mpl_svg/mpl_prototype.py
mpl_svg/mpl_svg.py
mpl_svg/render_test.py
mpl_svg-0.2.0.dist-info/LICENSE.txt
mpl_svg-0.2.0.dist-info/METADATA
mpl_svg-0.2.0.dist-info/WHEEL
mpl_svg-0.2.0.dist-info/top_level.txt
mpl_svg-0.2.0.dist-info/RECORD
