Metadata-Version: 2.1
Name: mpl-svg
Version: 0.2.0
Summary: Reformat Matplotlib SVGs for easier access and customzation with CSS
Home-page: https://github.com/bouzidanas/mpl-svg
Author: Anas Bouzid
Author-email: anasbouzid@gmail.com
Requires-Python: >=3.6
License-File: LICENSE.txt
Requires-Dist: matplotlib (>=3.2.1)
Requires-Dist: beautifulsoup4 (>=4.9.0)
